Metadata-Version: 2.1
Name: tvl-backends-opencv
Version: 0.1.0b18
Summary: UNKNOWN
Home-page: UNKNOWN
Author: Aiden Nibali
License: Apache Software License 2.0
Platform: UNKNOWN
License-File: LICENSE
Requires-Dist: tvl (==0.1.0b18)
Requires-Dist: numpy
Requires-Dist: torch
Requires-Dist: opencv-python
